ash_validity/Validator.py
ash_validity/ValidityLanguage.py
ash_validity/__init__.py
ash_validity/locale/en.json
ash_validity/locale/ur.json
ash_validity-1.0.0.dist-info/LICENSE
ash_validity-1.0.0.dist-info/METADATA
ash_validity-1.0.0.dist-info/WHEEL
ash_validity-1.0.0.dist-info/top_level.txt
ash_validity-1.0.0.dist-info/RECORD
